{
  "project_info": {
    "project_number": "1050613905469",
    "firebase_url": "https://chatpasto-77cff.firebaseio.com",
    "project_id": "chatpasto-77cff",
    "storage_bucket": "chatpasto-77cff.appspot.com"
  },
  "client": [
    {
      "client_info": {
        "mobilesdk_app_id": "1:1050613905469:android:6a3b1e788624efce265254",
        "android_client_info": {
          "package_name": "com.example.chatPasto"
        }
      },
      "oauth_client": [
        {
          "client_id": "1050613905469-p7ll7p3oekkpsjal8hvh4vilbelqkloh.apps.googleusercontent.com",
          "client_type": 3
        }
      ],
      "api_key": [
        {
          "current_key": "AIzaSyAc4_HUM4hOO4C2DTvp_kQIxindD-cKZtw"
        }
      ],
      "services": {
        "appinvite_service": {
          "other_platform_oauth_client": [
            {
              "client_id": "1050613905469-p7ll7p3oekkpsjal8hvh4vilbelqkloh.apps.googleusercontent.com",
              "client_type": 3
            }
          ]
        }
      }
    }
  ],
  "configuration_version": "1"
}